__init__.py
showexception/__init__.py
showexception/showexception.py
showexception/showexception_cli.py
showexception-0.1.1.dist-info/LICENSE
showexception-0.1.1.dist-info/METADATA
showexception-0.1.1.dist-info/WHEEL
showexception-0.1.1.dist-info/entry_points.txt
showexception-0.1.1.dist-info/top_level.txt
showexception-0.1.1.dist-info/RECORD
